{
  "events": [
    {
      "id": "1",
      "name": "Workshop React",
      "theme": "Front-end",
      "date": "20/05/2025",
      "image": "https://placehold.co/236x282"
    },
    {
      "id": "2",
      "name": "Conference JS",
      "theme": "Front-end",
      "date": "15/06/2025",
      "image": "https://placehold.co/236x282"
    },
    {
      "id": "3",
      "name": "Vue.js Masterclass",
      "theme": "Front-end",
      "date": "10/07/2025",
      "image": "https://placehold.co/236x282"
    },
    {
      "id": "4",
      "name": "Angular Workshop",
      "theme": "Front-end",
      "date": "25/07/2025",
      "image": "https://placehold.co/236x282"
    },
    {
      "isTrusted": true,
      "id": "CZfTuhMOh-E"
    },
    {
      "isTrusted": true,
      "id": "WLGMijFPYpU"
    },
    {
      "isTrusted": true,
      "id": "-Tftj9JjT5U"
    },
    {
      "isTrusted": true,
      "id": "XUuW39S1tC8"
    },
    {
      "isTrusted": true,
      "id": "fw5XP2WX4NQ"
    },
    {
      "isTrusted": true,
      "id": "IVqCiWKLatw"
    },
    {
      "isTrusted": true,
      "id": "VhOkwREA1jU"
    },
    {
      "isTrusted": true,
      "id": "YtnBnbB20Wk"
    },
    {
      "isTrusted": true,
      "id": "f_XQlyQYjog"
    },
    {
      "isTrusted": true,
      "id": "IZbK4UF0o-c"
    },
    {
      "isTrusted": true,
      "id": "QzNUcgdGzAA"
    },
    {
      "isTrusted": true,
      "id": "P4f_7IqgySI"
    },
    {
      "isTrusted": true,
      "id": "Z0Q9FDkgNP0"
    },
    {
      "isTrusted": true,
      "id": "85KCOnivCQI"
    },
    {
      "isTrusted": true,
      "id": "ZNI-uW0mzyk"
    },
    {
      "isTrusted": true,
      "id": "mZzFIFG5mo4"
    },
    {
      "isTrusted": true,
      "id": "MeFYlPKazaM"
    },
    {
      "isTrusted": true,
      "id": "8kAaxO4qBs0"
    },
    {
      "isTrusted": true,
      "id": "PkqRblFdYcI"
    },
    {
      "isTrusted": true,
      "id": "m5hzFT2Hw9w"
    },
    {
      "isTrusted": true,
      "id": "B_bHjc_MlyY"
    },
    {
      "isTrusted": true,
      "id": "LyuyjILVp3M"
    },
    {
      "isTrusted": true,
      "id": "eRuemhF7tuI"
    },
    {
      "isTrusted": true,
      "id": "8UmrrBInqh8"
    },
    {
      "isTrusted": true,
      "id": "oqUW5jTFbiA"
    }
  ],
  "$schema": "./node_modules/json-server/schema.json"
}